deep_audio_features
