Metadata-Version: 2.1
Name: deep-audio-features
Version: 0.2.15
Summary: Extract supervised deep features using CNN audio classifiers
Home-page: https://github.com/tyiannak/deep_audio_features
Author: Theodoros Giannakopoulos
Author-email: tyiannak@gmail.com
License: MIT
Platform: UNKNOWN
License-File: LICENSE
